leads_finder/__init__.py
leads_finder/core/__init__.py
leads_finder/core/cli.py
leads_finder/core/dedupe.py
leads_finder/core/export.py
leads_finder/core/parser.py
leads_finder/core/scraper_api_session.py
leads_finder/providers/__init__.py
leads_finder/providers/google_maps.py
leads_finder-1.0.1.dist-info/licenses/LICENSE
leads_finder-1.0.1.dist-info/METADATA
leads_finder-1.0.1.dist-info/WHEEL
leads_finder-1.0.1.dist-info/entry_points.txt
leads_finder-1.0.1.dist-info/top_level.txt
leads_finder-1.0.1.dist-info/RECORD
