Metadata-Version: 2.4
Name: leads-finder
Version: 1.0.1
Summary: Local business leads finder using Decodo proxies
Home-page: https://github.com/yousefkotp/local-leads-finder
Author: Yousef Kotp
Author-email: yousefkotp@outlook.com
Project-URL: Documentation, https://github.com/yousefkotp/local-leads-finder#readme
Project-URL: Source, https://github.com/yousefkotp/local-leads-finder
Project-URL: Issue Tracker, https://github.com/yousefkotp/local-leads-finder/issues
Project-URL: Releases, https://github.com/yousefkotp/local-leads-finder/releases
Project-URL: PyPI, https://pypi.org/project/leads-finder/
Classifier: Development Status :: 3 - Alpha
Classifier: Intended Audience :: Developers
Classifier: License :: OSI Approved :: MIT License
Classifier: Programming Language :: Python :: 3
Classifier: Programming Language :: Python :: 3.8
Classifier: Programming Language :: Python :: 3.9
Classifier: Programming Language :: Python :: 3.10
Classifier: Programming Language :: Python :: 3.11
Requires-Python: >=3.8
License-File: LICENSE
Requires-Dist: requests>=2.31.0
Requires-Dist: beautifulsoup4>=4.12.0
Requires-Dist: lxml>=4.9.0
Requires-Dist: python-Levenshtein>=0.21.0
Requires-Dist: python-dotenv>=1.0.0
Requires-Dist: click>=8.1.0
Dynamic: author
Dynamic: author-email
Dynamic: classifier
Dynamic: description
Dynamic: description-content-type
Dynamic: home-page
Dynamic: license-file
Dynamic: project-url
Dynamic: requires-dist
Dynamic: requires-python
Dynamic: summary
